CHANGES.txt
COPYRIGHT.txt
LICENSE.txt
MANIFEST.in
README.txt
buildout.cfg
setup.py
src/p01/__init__.py
src/p01.jsonrpc.egg-info/PKG-INFO
src/p01.jsonrpc.egg-info/SOURCES.txt
src/p01.jsonrpc.egg-info/dependency_links.txt
src/p01.jsonrpc.egg-info/namespace_packages.txt
src/p01.jsonrpc.egg-info/not-zip-safe
src/p01.jsonrpc.egg-info/requires.txt
src/p01.jsonrpc.egg-info/top_level.txt
src/p01/jsonrpc/README.txt
src/p01/jsonrpc/__init__.py
src/p01/jsonrpc/browser.py
src/p01/jsonrpc/configure.zcml
src/p01/jsonrpc/error.py
src/p01/jsonrpc/error.zcml
src/p01/jsonrpc/exception.py
src/p01/jsonrpc/ftesting.zcml
src/p01/jsonrpc/interfaces.py
src/p01/jsonrpc/layer.py
src/p01/jsonrpc/meta.zcml
src/p01/jsonrpc/namespace.py
src/p01/jsonrpc/publication.py
src/p01/jsonrpc/publisher.py
src/p01/jsonrpc/testing.py
src/p01/jsonrpc/zcml.py
src/p01/jsonrpc/zcml.txt
src/p01/jsonrpc/tests/__init__.py
src/p01/jsonrpc/tests/page.pt
src/p01/jsonrpc/tests/test_doc.py
src/p01/jsonrpc/tests/test_factory.py
src/p01/jsonrpc/tests/test_request.py