Metadata-Version: 2.1
Name: p01.jsonrpc
Version: 0.8.1
Summary: JSON RPC server and client implementation for Zope3
Home-page: http://pypi.python.org/pypi/p01.jsonrpc
Author: Roger Ineichen and the Zope Community
Author-email: zope-dev@zope.org
License: ZPL 2.1
Keywords: zope3 z3c p01 json rpc json-rpc server client
Platform: UNKNOWN
Classifier: Development Status :: 5 - Production/Stable
Classifier: Environment :: Web Environment
Classifier: Intended Audience :: Developers
Classifier: License :: OSI Approved :: Zope Public License
Classifier: Programming Language :: Python
Classifier: Natural Language :: English
Classifier: Operating System :: OS Independent
Classifier: Topic :: Internet :: WWW/HTTP
Classifier: Framework :: Zope :: 3
Provides-Extra: test
